LICENSE.txt
README.md
setup.cfg
setup.py
os_android_launcher_creator/ImgObj.py
os_android_launcher_creator/launcher_creator.py
os_android_launcher_creator/test.py
os_android_launcher_creator.egg-info/PKG-INFO
os_android_launcher_creator.egg-info/SOURCES.txt
os_android_launcher_creator.egg-info/dependency_links.txt
os_android_launcher_creator.egg-info/requires.txt
os_android_launcher_creator.egg-info/top_level.txt
os_android_launcher_creator/bp/_launcher_creator.py
os_android_launcher_creator/bp/_vector_creator.py