Metadata-Version: 2.1
Name: os_android_launcher_creator
Version: 1.14
Summary: This module will create an app launcher (logo) using Android Studio in all sizes and shapes (web, round) and in all dpi (mipmap-anydpi-v26, mipmap-hdpi, mipmap-mdpi, mipmap-xhdpi, mipmap-xxhdpi, mipmap-xxxhdpi, values)
Home-page: https://github.com/osfunapps/os_android_launcher_creator-py
Author: Oz Shabat
Author-email: admin@os-apps.com
License: MIT
Keywords: python,osfunapps,osapps,automation,logo,app launcher,os_file_stream_handler
Classifier: Development Status :: 5 - Production/Stable
Classifier: Intended Audience :: Developers
Classifier: Topic :: Software Development :: Build Tools
Classifier: License :: OSI Approved :: MIT License
Classifier: Programming Language :: Python :: 3
Classifier: Programming Language :: Python :: 3.4
Classifier: Programming Language :: Python :: 3.5
Classifier: Programming Language :: Python :: 3.6
Classifier: Programming Language :: Python :: 3.9
License-File: LICENSE.txt
Requires-Dist: os_tools
Requires-Dist: os_file_handler
Requires-Dist: os-btns-automation
